serp_api_mcp/__init__.py
serp_api_mcp/config.py
serp_api_mcp/server.py
serp_api_mcp/models/__init__.py
serp_api_mcp/models/schemas.py
serp_api_mcp/services/__init__.py
serp_api_mcp/services/search_service.py
serp_api_mcp/utils/__init__.py
serp_api_mcp/utils/logging.py
serp_api_mcp-0.1.1.dist-info/METADATA
serp_api_mcp-0.1.1.dist-info/WHEEL
serp_api_mcp-0.1.1.dist-info/entry_points.txt
serp_api_mcp-0.1.1.dist-info/RECORD
